{
  "fetchCurrentUser": {
    "token": "eyJhbGciOiJIUzI1NiIsInR5cCI6IkpXVCJ9.eyJ1c2VyTmFtZSI6ImFkbWluIiwicGFzc1dvcmQiOiIxMjMiLCJpYXQiOjE2NDQ5MTYyNjIsImV4cCI6MTY0NDkxOTg2Mn0.yB-giAPW47v5x0zjq0OhuAZl5nyH5DMIL0SStQluWQs"
  },
  "templates": [
    {
      "id": 0,
      "title": "哈哈哈哈",
      "coverImg": "",
      "author": "test",
      "copiedCount": 0,
      "description": "description",
      "authorImg": ""
    },
    {
      "id": 1,
      "title": "title222",
      "coverImg": "",
      "author": "test222",
      "copiedCount": 0,
      "description": "description222",
      "authorImg": ""
    },
    {
      "id": 3,
      "title": "title3333",
      "coverImg": "",
      "author": "test333",
      "copiedCount": 0,
      "description": "description333",
      "authorImg": ""
    }
  ],
  "work": [
    {
      "id": 1,
      "content": {
        "components": [
          {
            "props": {
              "text": "大标题",
              "fontSize": "30px",
              "fontFamily": "",
              "fontWeight": "bold",
              "fontStyle": "",
              "textDecoration": "",
              "lineHeight": "",
              "textAlign": "",
              "color": "",
              "backgroundColor": "",
              "actionType": "",
              "url": "",
              "height": "",
              "width": "100px",
              "paddingLeft": "0px",
              "paddingRight": "0px",
              "paddingTop": "0px",
              "paddingBottom": "0px",
              "borderStyle": "none",
              "borderColor": "#000",
              "borderWidth": "0",
              "borderRadius": "0",
              "boxShadow": "0 0 0 #000000",
              "opacity": "1",
              "position": "absolute",
              "left": "114px",
              "top": "309px",
              "right": "0",
              "tag": "h2"
            },
            "name": "l-text",
            "id": "ae8760cc-43e9-4b57-b462-76dc9d601fc3",
            "isHide": false,
            "isLock": false,
            "layerName": "图层1"
          },
          {
            "props": {
              "text": "正文内容",
              "fontSize": "30px",
              "fontFamily": "",
              "fontWeight": "",
              "fontStyle": "",
              "textDecoration": "",
              "lineHeight": "",
              "textAlign": "",
              "color": "",
              "backgroundColor": "",
              "actionType": "",
              "url": "",
              "height": "",
              "width": "100px",
              "paddingLeft": "0px",
              "paddingRight": "0px",
              "paddingTop": "0px",
              "paddingBottom": "0px",
              "borderStyle": "none",
              "borderColor": "#000",
              "borderWidth": "0",
              "borderRadius": "0",
              "boxShadow": "0 0 0 #000000",
              "opacity": "1",
              "position": "absolute",
              "left": "167px",
              "top": "42px",
              "right": "0",
              "tag": "p"
            },
            "name": "l-text",
            "id": "d155bbdd-78d1-41b7-9d3b-a5d774f0666e",
            "isHide": false,
            "isLock": false,
            "layerName": "图层2"
          },
          {
            "props": {
              "text": "链接内容",
              "fontSize": "30px",
              "fontFamily": "",
              "fontWeight": "",
              "fontStyle": "",
              "textDecoration": "underline",
              "lineHeight": "",
              "textAlign": "",
              "color": "#1890ff",
              "backgroundColor": "",
              "actionType": "",
              "url": "",
              "height": "",
              "width": "100px",
              "paddingLeft": "0px",
              "paddingRight": "0px",
              "paddingTop": "0px",
              "paddingBottom": "0px",
              "borderStyle": "none",
              "borderColor": "#000",
              "borderWidth": "0",
              "borderRadius": "0",
              "boxShadow": "0 0 0 #000000",
              "opacity": "1",
              "position": "absolute",
              "left": "91px",
              "top": "140px",
              "right": "0",
              "tag": "p"
            },
            "name": "l-text",
            "id": "79141ace-c901-418c-8ac4-1fe64c846c29",
            "isHide": false,
            "isLock": false,
            "layerName": "图层3"
          }
        ],
        "props": {
          "background-color": "#ffffff",
          "background-image": "",
          "background-repeat": "no-repeat",
          "background-size": "cover",
          "height": "530px"
        }
      }
    }
  ]
}